{
  "hash": "9ee27d58",
  "configHash": "faefbc90",
  "lockfileHash": "5975fc81",
  "browserHash": "e1957d2e",
  "optimized": {
    "vue": {
      "src": "../../../node_modules/.pnpm/vue@3.5.13/node_modules/vue/dist/vue.runtime.esm-bundler.js",
      "file": "vue.js",
      "fileHash": "7e324ea6",
      "needsInterop": false
    },
    "vitepress > @vue/devtools-api": {
      "src": "../../../node_modules/.pnpm/@vue+devtools-api@7.7.0/node_modules/@vue/devtools-api/dist/index.js",
      "file": "vitepress___@vue_devtools-api.js",
      "fileHash": "3f8adbea",
      "needsInterop": false
    },
    "vitepress > @vueuse/core": {
      "src": "../../../node_modules/.pnpm/@vueuse+core@11.3.0_vue@3.5.13/node_modules/@vueuse/core/index.mjs",
      "file": "vitepress___@vueuse_core.js",
      "fileHash": "5094cc5f",
      "needsInterop": false
    },
    "vitepress > @vueuse/integrations/useFocusTrap": {
      "src": "../../../node_modules/.pnpm/@vueuse+integrations@11.3.0_focus-trap@7.6.4_vue@3.5.13/node_modules/@vueuse/integrations/useFocusTrap.mjs",
      "file": "vitepress___@vueuse_integrations_useFocusTrap.js",
      "fileHash": "20908b40",
      "needsInterop": false
    },
    "vitepress > mark.js/src/vanilla.js": {
      "src": "../../../node_modules/.pnpm/mark.js@8.11.1/node_modules/mark.js/src/vanilla.js",
      "file": "vitepress___mark__js_src_vanilla__js.js",
      "fileHash": "e7d1743c",
      "needsInterop": false
    },
    "vitepress > minisearch": {
      "src": "../../../node_modules/.pnpm/minisearch@7.1.1/node_modules/minisearch/dist/es/index.js",
      "file": "vitepress___minisearch.js",
      "fileHash": "ffc2f79d",
      "needsInterop": false
    },
    "oh-my-live2d": {
      "src": "../../../node_modules/.pnpm/oh-my-live2d@0.19.3/node_modules/oh-my-live2d/dist/index.js",
      "file": "oh-my-live2d.js",
      "fileHash": "ff64afe8",
      "needsInterop": false
    },
    "canvas-confetti": {
      "src": "../../../node_modules/.pnpm/canvas-confetti@1.9.3/node_modules/canvas-confetti/dist/confetti.module.mjs",
      "file": "canvas-confetti.js",
      "fileHash": "ac42e835",
      "needsInterop": false
    }
  },
  "chunks": {
    "chunk-23MPOIE3": {
      "file": "chunk-23MPOIE3.js"
    },
    "chunk-CQOUZRMK": {
      "file": "chunk-CQOUZRMK.js"
    },
    "chunk-BUSYA2B4": {
      "file": "chunk-BUSYA2B4.js"
    }
  }
}